shpowerpeakpredict/__init__.py
shpowerpeakpredict/shpower_predict_peak.py
shpowerpeakpredict/shsqlpeak.py
sh_powerpeak_predict-1.0.0.1.dist-info/METADATA
sh_powerpeak_predict-1.0.0.1.dist-info/WHEEL
sh_powerpeak_predict-1.0.0.1.dist-info/top_level.txt
sh_powerpeak_predict-1.0.0.1.dist-info/RECORD
